dploot/__init__.py
dploot/action/__init__.py
dploot/action/backupkey.py
dploot/action/blob.py
dploot/action/browser.py
dploot/action/certificates.py
dploot/action/credentials.py
dploot/action/machinecertificates.py
dploot/action/machinecredentials.py
dploot/action/machinemasterkeys.py
dploot/action/machinetriage.py
dploot/action/machinevaults.py
dploot/action/masterkeys.py
dploot/action/mobaxterm.py
dploot/action/rdg.py
dploot/action/sccm.py
dploot/action/triage.py
dploot/action/vaults.py
dploot/action/wam.py
dploot/action/wifi.py
dploot/entry.py
dploot/lib/__init__.py
dploot/lib/consts.py
dploot/lib/crypto.py
dploot/lib/dpapi.py
dploot/lib/masterkey.py
dploot/lib/smb.py
dploot/lib/target.py
dploot/lib/utils.py
dploot/lib/wmi.py
dploot/triage/__init__.py
dploot/triage/backupkey.py
dploot/triage/browser.py
dploot/triage/certificates.py
dploot/triage/credentials.py
dploot/triage/masterkeys.py
dploot/triage/mobaxterm.py
dploot/triage/rdg.py
dploot/triage/sccm.py
dploot/triage/vaults.py
dploot/triage/wam.py
dploot/triage/wifi.py
dploot-3.1.3.dist-info/LICENSE
dploot-3.1.3.dist-info/METADATA
dploot-3.1.3.dist-info/WHEEL
dploot-3.1.3.dist-info/entry_points.txt
dploot-3.1.3.dist-info/RECORD
