Metadata-Version: 2.3
Name: dploot
Version: 3.1.3
Summary: DPAPI looting remotely in Python
License: MIT
Keywords: DPAPI,credentials,Windows
Author: zblurx
Author-email: seigneuret.thomas@protonmail.com
Requires-Python: >=3.10.0,<4.0.0
Classifier: Environment :: Console
Classifier: License :: OSI Approved :: MIT License
Classifier: Programming Language :: Python :: 3
Classifier: Programming Language :: Python :: 3.10
Classifier: Programming Language :: Python :: 3.11
Classifier: Programming Language :: Python :: 3.12
Classifier: Programming Language :: Python :: 3.13
Classifier: Topic :: Security
Requires-Dist: cryptography (>=40.0.1)
Requires-Dist: impacket (>=0.12.0)
Requires-Dist: lxml (>=5.0)
Requires-Dist: pyasn1 (>=0.4.8)
Project-URL: Homepage, https://github.com/zblurx/dploot
Project-URL: Repository, https://github.com/zblurx/dploot
